{"messageId":"dash-1774509006","timestamp":"2026-03-26T07:10:07.107611","response":{"airPurifierJobMode":{"currentJobMode":"AUTO"},"operation":{"airPurifierOperationMode":"POWER_ON"},"timer":{"absoluteStartTimer":"UNSET","absoluteStopTimer":"UNSET"},"sleepTimer":{"relativeStopTimer":"UNSET"},"airFlow":{"windStrength":"AUTO","windStrengthDetail":"AUTO"},"airQualitySensor":{"monitoringEnabled":"ALWAYS","PM1":10,"PM2":12,"PM10":20,"PM1Level":"GOOD","PM2Level":"GOOD","PM10Level":"GOOD","oder":2,"odor":2,"odorLevel":"NORMAL","totalPollution":2,"totalPollutionLevel":"NORMAL"},"filterInfo":{"topFilterRemainPercent":64,"filterRemainPercent":17}}}
