{"messageId":"dash-1774535102","timestamp":"2026-03-26T14:25:02.962862","response":{"airPurifierJobMode":{"currentJobMode":"AUTO"},"operation":{"airPurifierOperationMode":"POWER_ON"},"timer":{"absoluteStartTimer":"UNSET","absoluteStopTimer":"UNSET"},"sleepTimer":{"relativeStopTimer":"UNSET"},"airFlow":{"windStrength":"AUTO","windStrengthDetail":"AUTO"},"airQualitySensor":{"monitoringEnabled":"ALWAYS","PM1":24,"PM2":27,"PM10":27,"PM1Level":"MODERATE","PM2Level":"MODERATE","PM10Level":"GOOD","oder":1,"odor":1,"odorLevel":"WEAK","totalPollution":2,"totalPollutionLevel":"NORMAL"},"filterInfo":{"topFilterRemainPercent":64,"filterRemainPercent":17}}}
